pydamapper/__init__.py
pydamapper/pydamapper.py
pydamapper/src/.gitignore
pydamapper/src/__init__.py
pydamapper/src/error_manager.py
pydamapper/src/error_registry.py
pydamapper/src/exceptions.py
pydamapper/src/field_cache.py
pydamapper/src/field_matcher.py
pydamapper/src/logger_config.py
pydamapper/src/meta_field.py
pydamapper/src/path_manager.py
pydamapper/src/traverse.py
pydamapper/src/types.py
pydamapper/src/utils.py
pydamapper-0.1.0.dist-info/METADATA
pydamapper-0.1.0.dist-info/WHEEL
pydamapper-0.1.0.dist-info/licenses/LICENSE
pydamapper-0.1.0.dist-info/RECORD
