Metadata-Version: 2.4
Name: pydamapper
Version: 0.1.0
Summary: Map data between pydantic models
Project-URL: Homepage, https://github.com/julioccorderoc/pydamapper
Project-URL: Issues, https://github.com/julioccorderoc/pydamapper/issues
Project-URL: Source, https://github.com/julioccorderoc/pydamapper
Author-email: Julio Cordero <julioccorderoc@gmail.com>
License-Expression: MIT
License-File: LICENSE
Keywords: data,mapping,model,pydantic
Classifier: Development Status :: 3 - Alpha
Classifier: Framework :: Pydantic
Classifier: Framework :: Pytest
Classifier: Intended Audience :: Developers
Classifier: License :: OSI Approved :: MIT License
Classifier: Natural Language :: English
Classifier: Operating System :: OS Independent
Classifier: Programming Language :: Python
Classifier: Topic :: File Formats :: JSON
Classifier: Topic :: Software Development :: Libraries :: Python Modules
Classifier: Topic :: Software Development :: Object Brokering
Requires-Python: >=3.13
Requires-Dist: pydantic>=2.10.6
